LICENSE.txt
MANIFEST.in
README.md
setup.cfg
setup.py
missing_values_antuanant/__init__.py
missing_values_antuanant/missing_values.py
missing_values_antuanant.egg-info/PKG-INFO
missing_values_antuanant.egg-info/SOURCES.txt
missing_values_antuanant.egg-info/dependency_links.txt
missing_values_antuanant.egg-info/top_level.txt