Metadata-Version: 2.1
Name: missing-values-antuanant
Version: 0.0.1
Summary: Technique for filling Missing values
Home-page: https://github.com/Anant99-sys/Missing-values
Author: Anant Chopra
Author-email: anantchopra95@gmail.com
License: UNKNOWN
Platform: UNKNOWN
Classifier: Programming Language :: Python :: 3
Classifier: License :: OSI Approved :: MIT License
Classifier: Operating System :: OS Independent
Requires-Python: >=3.7
